KnotLinkClient_PyQt/OpenSocketQuerier.py
KnotLinkClient_PyQt/OpenSocketResponser.py
KnotLinkClient_PyQt/SignalSender.py
KnotLinkClient_PyQt/SignalSubscriber.py
KnotLinkClient_PyQt/__init__.py
KnotLinkClient_PyQt/tcpclient.py
knotlinkclient_pyqt-1.0.0.dist-info/METADATA
knotlinkclient_pyqt-1.0.0.dist-info/WHEEL
knotlinkclient_pyqt-1.0.0.dist-info/top_level.txt
knotlinkclient_pyqt-1.0.0.dist-info/RECORD
