Metadata-Version: 2.2
Name: KnotLinkClient_PyQt
Version: 1.0.0
Summary: A PyQt-based client for KnotLink communication
Author: HXH
Author-email: 1768224274@qq.com
Classifier: Programming Language :: Python :: 3
Classifier: Operating System :: OS Independent
Classifier: Topic :: Software Development :: Libraries :: Python Modules
Classifier: Intended Audience :: Developers
Requires-Dist: PyQt5>=5.15.0
Dynamic: author
Dynamic: author-email
Dynamic: classifier
Dynamic: description
Dynamic: description-content-type
Dynamic: requires-dist
Dynamic: summary
